docktdeep/__init__.py
docktdeep/cli.py
docktdeep/dataset.py
docktdeep/inference.py
docktdeep/transforms.py
docktdeep/models/__init__.py
docktdeep/models/baseline.py
docktdeep/models/stn.py
docktdeep-0.1.1.dist-info/licenses/COPYING.LESSER
docktdeep-0.1.1.dist-info/METADATA
docktdeep-0.1.1.dist-info/WHEEL
docktdeep-0.1.1.dist-info/entry_points.txt
docktdeep-0.1.1.dist-info/top_level.txt
docktdeep-0.1.1.dist-info/RECORD
