Metadata-Version: 2.4
Name: docktdeep
Version: 0.1.1
Summary: A deep learning model for protein-ligand binding affinity prediction
Author-email: "Matheus M. P. da Silva" <matheusp@posgrad.lncc.br>
License: LGPL-2.1-or-later
Project-URL: Homepage, https://github.com/gmmsb-lncc/docktdeep
Project-URL: Repository, https://github.com/gmmsb-lncc/docktdeep
Project-URL: Issues, https://github.com/gmmsb-lncc/docktdeep/issues
Keywords: protein-ligand,binding-affinity,deep-learning,drug-discovery
Classifier: Development Status :: 3 - Alpha
Classifier: Intended Audience :: Science/Research
Classifier: Operating System :: OS Independent
Classifier: Programming Language :: Python :: 3
Classifier: Programming Language :: Python :: 3.8
Classifier: Programming Language :: Python :: 3.9
Classifier: Programming Language :: Python :: 3.10
Classifier: Programming Language :: Python :: 3.11
Classifier: Programming Language :: Python :: 3.12
Classifier: Topic :: Scientific/Engineering :: Bio-Informatics
Classifier: Topic :: Scientific/Engineering :: Chemistry
Requires-Python: >=3.8
License-File: COPYING.LESSER
Requires-Dist: torch>=2.0.0
Requires-Dist: numpy>=1.21.0
Requires-Dist: tqdm>=4.60.0
Requires-Dist: pytorch-lightning>=2.0.0
Requires-Dist: lightning>=2.5.0
Requires-Dist: docktgrid>=0.0.3
Requires-Dist: biopandas>=0.4.0
Requires-Dist: pandas>=1.3.0
Provides-Extra: full
Requires-Dist: aim>=3.29.0; extra == "full"
Requires-Dist: lightning>=2.5.0; extra == "full"
Requires-Dist: torchmetrics>=1.8.0; extra == "full"
Requires-Dist: scipy>=1.16.0; extra == "full"
Provides-Extra: dev
Requires-Dist: pytest>=6.0; extra == "dev"
Requires-Dist: black>=21.0; extra == "dev"
Requires-Dist: flake8>=3.8; extra == "dev"
Requires-Dist: mypy>=0.910; extra == "dev"
Dynamic: license-file
